pembot/.gitignore
pembot/LICENSE
pembot/__init__.py
pembot/gartner.py
pembot/main.py
pembot/output_structure_local.py
pembot/pem.py
pembot/pyrightconfig.json
pembot/query.py
pembot/requirements.txt
pembot/search.py
pembot/.git/COMMIT_EDITMSG
pembot/.git/HEAD
pembot/.git/config
pembot/.git/description
pembot/.git/index
pembot/.git/packed-refs
pembot/.git/hooks/applypatch-msg.sample
pembot/.git/hooks/commit-msg.sample
pembot/.git/hooks/fsmonitor-watchman.sample
pembot/.git/hooks/post-update.sample
pembot/.git/hooks/pre-applypatch.sample
pembot/.git/hooks/pre-commit.sample
pembot/.git/hooks/pre-merge-commit.sample
pembot/.git/hooks/pre-push.sample
pembot/.git/hooks/pre-rebase.sample
pembot/.git/hooks/pre-receive.sample
pembot/.git/hooks/prepare-commit-msg.sample
pembot/.git/hooks/push-to-checkout.sample
pembot/.git/hooks/sendemail-validate.sample
pembot/.git/hooks/update.sample
pembot/.git/info/exclude
pembot/.git/logs/HEAD
pembot/.git/logs/refs/heads/main
pembot/.git/logs/refs/remotes/origin/HEAD
pembot/.git/logs/refs/remotes/origin/main
pembot/.git/objects/00/3ba85af0ed7b9f6ab099ca298c3d0c18fb002b
pembot/.git/objects/01/5f71967c525963c827d7fe5415ae2c040c4a64
pembot/.git/objects/05/5e82e69847a636258cb994bb920c03a93b5ff4
pembot/.git/objects/06/f7563094fe405dfd9c69f05e357f4e20fc5979
pembot/.git/objects/09/ee34d94dffd4c286df1d6d528b2e98e2a6cce2
pembot/.git/objects/0a/2121ea3115562cc205df572ea26532aaac5244
pembot/.git/objects/0a/6dd69f9258bba08a669efec17ff170fdd1509e
pembot/.git/objects/0a/fb3a98cdc55b1434b44534ec2bf22c56cfa26c
pembot/.git/objects/0b/db4169fc0f312b8698f1df17a258fff163aeaa
pembot/.git/objects/0c/8d9b2690545bf1906b05cd9f18b783b3eb74f1
pembot/.git/objects/0c/ab66ffbaf50ef60dd41f3498595ebd2526b33c
pembot/.git/objects/0d/28f73897db0c9a9351ee9e64d2a0fe27db2705
pembot/.git/objects/0e/120123bfadfd594220963f3bbca54056bab6ee
pembot/.git/objects/0e/6b7f7409a88aa2595206b53112a666e4dca8a2
pembot/.git/objects/0f/ccea3d0db4864a854f8b2c13b9f76b3601d200
pembot-0.1.8.dist-info/licenses/LICENSE
pembot-0.1.8.dist-info/WHEEL
pembot-0.1.8.dist-info/METADATA
pembot-0.1.8.dist-info/RECORD
