Metadata-Version: 2.4
Name: pembot
Version: 0.1.8
Summary: A Python Package to convert PEM blog content to usseful information by leveraging LLMs
Author-email: cyto <aryan_sidhwani@protonmail.com>
License-Expression: MIT
License-File: LICENSE
Project-URL: Home, https://github.com/silverstone-git/pem-rag-chatbot
